spotmux/__init__.py
spotmux/spotmux.py
spotmux/helper/__init__.py
spotmux/helper/settings.py
spotmux/helper/spotify_countries.py
spotmux/helper/spotify_markets.py
spotmux/helper/streaming_thread.py
spotmux/helper/thread_utils.py
spotmux/helper/utils.py
spotmux/managers/__init__.py
spotmux/managers/data_manager.py
spotmux/managers/mongodb_manager.py
spotmux/managers/music_manager.py
spotmux/managers/musicmatch_manager.py
spotmux/managers/spotify_manager.py
spotmux/models/__init__.py
spotmux/models/doument_models.py
SpotMux-1.0.4.dist-info/LICENSE.txt
SpotMux-1.0.4.dist-info/METADATA
SpotMux-1.0.4.dist-info/WHEEL
SpotMux-1.0.4.dist-info/top_level.txt
SpotMux-1.0.4.dist-info/RECORD
